sparkxarray/__init__.py
sparkxarray/reader.py
sparkxarray/tests/__init__.py
sparkxarray/tests/test_reader.py
spark_xarray-0.1.dev0.dist-info/LICENSE
spark_xarray-0.1.dev0.dist-info/METADATA
spark_xarray-0.1.dev0.dist-info/WHEEL
spark_xarray-0.1.dev0.dist-info/top_level.txt
spark_xarray-0.1.dev0.dist-info/RECORD
