Metadata-Version: 2.1
Name: spark-xarray
Version: 0.1.dev0
Home-page: https://github.com/andersy005/spark-xarray
Author: Anderson Banihirwe, Kevin Paul
Author-email: axbanihirwe@gmail.com
Keywords: Climate Science,xarray,Apache Spark,Distributed,netCDF,Parallel
Classifier: Intended Audience :: Science/Research
Classifier: Natural Language :: English
Classifier: Operating System :: OS Independent
Classifier: Programming Language :: Python :: 2.7
Classifier: Programming Language :: Python :: 3
Classifier: Programming Language :: Python :: 3.4
Classifier: Programming Language :: Python :: 3.5
Classifier: Programming Language :: Python :: 3.6
Classifier: Topic :: Scientific/Engineering :: Atmospheric Science
License-File: LICENSE
Requires-Dist: numpy >=1.7
Requires-Dist: scipy >=0.16
Requires-Dist: pandas >=0.15.0
Requires-Dist: netCDF4 >=1.2
Requires-Dist: xarray >=0.9.5
Requires-Dist: dask >=0.14
Requires-Dist: distributed >=1.16.1
Requires-Dist: geopandas >=0.3.0
Requires-Dist: toolz >=0.8.2
Requires-Dist: cloudpickle >=0.2.1
